total_netwk/__init__.py
total_netwk/basic_index_dict.py
total_netwk/clifin.py
total_netwk/create_network.py
total_netwk/filter_sequence.py
total_netwk/find_community_byhost.py
total_netwk-0.1.dist-info/LICENSE.txt
total_netwk-0.1.dist-info/METADATA
total_netwk-0.1.dist-info/WHEEL
total_netwk-0.1.dist-info/top_level.txt
total_netwk-0.1.dist-info/RECORD
