Metadata-Version: 2.1
Name: total-netwk
Version: 0.1
Summary: A package for network analysis and community detection
Author: Gongruihao
Author-email: 202031200039@mail.bnu.edu.cn
License: MIT
Classifier: Development Status :: 4 - Beta
Classifier: Intended Audience :: Developers
Classifier: License :: OSI Approved :: MIT License
Classifier: Programming Language :: Python :: 3
Classifier: Programming Language :: Python :: 3.8
Classifier: Programming Language :: Python :: 3.9
Classifier: Programming Language :: Python :: 3.10
Requires-Python: >=3.8
License-File: LICENSE.txt
Requires-Dist: networkx
